cloe_util_snowflake_connector/__init__.py
cloe_util_snowflake_connector/connection_parameters.py
cloe_util_snowflake_connector/py.typed
cloe_util_snowflake_connector/snowflake_interface.py
cloe_util_snowflake_connector/utils.py
cloe_util_snowflake_connector-1.0.6.dist-info/METADATA
cloe_util_snowflake_connector-1.0.6.dist-info/WHEEL
cloe_util_snowflake_connector-1.0.6.dist-info/RECORD
